castordashboard/__init__.py
castordashboard/dashboard/__init__.py
castordashboard/dashboard/manage.py
castordashboard/dashboard/app/__init__.py
castordashboard/dashboard/app/admin.py
castordashboard/dashboard/app/apps.py
castordashboard/dashboard/app/models.py
castordashboard/dashboard/app/tests.py
castordashboard/dashboard/app/urls.py
castordashboard/dashboard/app/views.py
castordashboard/dashboard/app/migrations/__init__.py
castordashboard/dashboard/dashboard/__init__.py
castordashboard/dashboard/dashboard/settings.py
castordashboard/dashboard/dashboard/urls.py
castordashboard/dashboard/dashboard/wsgi.py
castordashboard/etl/__init__.py
castordashboard/etl/script_runner.py
castordashboard/etl/scripts/__init__.py
castordashboard/etl/scripts/basescript.py
castordashboard/etl/scripts/dummyscript.py
castordashboard/etl/scripts/retrieveprocedurecountsandcomplicationsperquarterscript.py
castordashboard/etl/scripts/retrievestudylistscript.py
castordashboard-2.2.2.data/scripts/run_castordashboard_etl.sh
castordashboard-2.2.2.dist-info/AUTHORS.rst
castordashboard-2.2.2.dist-info/LICENSE
castordashboard-2.2.2.dist-info/METADATA
castordashboard-2.2.2.dist-info/WHEEL
castordashboard-2.2.2.dist-info/entry_points.txt
castordashboard-2.2.2.dist-info/top_level.txt
castordashboard-2.2.2.dist-info/RECORD
