Metadata-Version: 2.1
Name: castordashboard
Version: 2.2.2
Summary: Dashboard application that extracts data from Castor and displays it
Home-page: https://github.com/rbrecheisen/castordashboard
Author: Ralph Brecheisen
Author-email: ralph.brecheisen@gmail.com
License: MIT license
Keywords: castordashboard
Platform: UNKNOWN
Classifier: Development Status :: 2 - Pre-Alpha
Classifier: Intended Audience :: Developers
Classifier: License :: OSI Approved :: MIT License
Classifier: Natural Language :: English
Classifier: Programming Language :: Python :: 3
Classifier: Programming Language :: Python :: 3.5
Classifier: Programming Language :: Python :: 3.6
Classifier: Programming Language :: Python :: 3.7
Classifier: Programming Language :: Python :: 3.8
Requires-Python: >=3.5
Requires-Dist: barbell2
Requires-Dist: pytest
Requires-Dist: numpy
Requires-Dist: bokeh (==2.3.0)
Requires-Dist: django (==3.1.7)
Requires-Dist: django-session-security (==2.6.6)
